[
    {
        "src": "music/Beck-Dark_Places.mp3",
        "trackName": "Beck - Dark Place",
        "genre": "Rock",
        "album" : "Hyperspace",
        "rating": []
    },
    {
        "src": "music/Beck-Die_Waiting.mp3",
        "trackName": "Beck - Die Waiting",
        "genre": "Rock",
        "album" : "Hyperspace",
        "rating": []
    },
    {
        "src": "music/Beck-Everlasting_Nothing.mp3",
        "trackName": "Beck - Everlasting Nothing",
        "genre": "Rock",
        "album" : "Hyperspace",
        "rating": []
    },
    {
        "src": "music/Beck-Chemical.mp3",
        "trackName": "Beck - Chemical",
        "genre": "Rock",
        "album" : "Hyperspace",
        "rating": []
    },
    {
        "src": "music/Beck-Hyperlife.mp3",
        "trackName": "Beck - Hiperlife",
        "genre": "Rock",
        "album" : "Hyperspace",
        "rating": []
    },
    {
        "src": "music/Beck-Hyperspace_feat_Terrell_Hines.mp3",
        "trackName": "Beck - Hyperspace",
        "genre": "Rock",
        "album" : "Hyperspace",
        "rating": []
    },
    {
        "src": "music/Beck-Saw_Lightning.mp3",
        "trackName": "Beck - Lightning",
        "genre": "Rock",
        "album" : "Hyperspace",
        "rating": []
    },
    {
        "src": "music/Beck-See_Through.mp3",
        "trackName": "Beck - Through",
        "genre": "Rock",
        "album" : "Hyperspace",
        "rating": []
    },
    {
        "src": "music/Beck-Star.mp3",
        "trackName": "Beck - Star",
        "genre": "Rock",
        "album" : "Hyperspace",
        "rating": []
    },
    {
        "src": "music/Beck-Stratosphere.mp3",
        "trackName": "Beck - Stratosphere",
        "genre": "Rock",
        "album" : "Hyperspace",
        "rating": []
    },
    {
        "src": "music/Beck-Uneventful_Days.mp3",
        "trackName": "Beck - Uneventful Days",
        "genre": "Rock",
        "album" : "Hyperspace",
        "rating": []
    },
    {
        "src": "music/Burial-Ashtray_wasp.mp3",
        "trackName": "Burial - Ashtray wasp",
        "genre": "Dubstep",
        "album" : "Tunes 2011-2019",
        "rating": []
    },
    {
        "src": "music/Burial-Beachfires.mp3",
        "trackName": "Burial - Beachfires",
        "genre": "Dubstep",
        "album" : "Tunes 2011-2019",
        "rating": []
    },
    {
        "src": "music/Burial-Claustro.mp3",
        "trackName": "Burial - Claustro",
        "genre": "Dubstep",
        "album" : "Tunes 2011-2019",
        "rating": []
    },
    {
        "src": "music/Burial-Come_down_to_us.mp3",
        "trackName": "Burial - Come down to us",
        "genre": "Dubstep",
        "album" : "Tunes 2011-2019",
        "rating": []
    },
    {
        "src": "music/Burial-Hiders.mp3",
        "trackName": "Burial - Hiders",
        "genre": "Dubstep",
        "album" : "Tunes 2011-2019",
        "rating": []
    },
    {
        "src": "music/Burial-Kindred.mp3",
        "trackName": "Burial - Kindred",
        "genre": "Dubstep",
        "album" : "Tunes 2011-2019",
        "rating": []
    },
    {
        "src": "music/Burial-Loner.mp3",
        "trackName": "Burial - Loner",
        "genre": "Dubstep",
        "album" : "Tunes 2011-2019",
        "rating": []
    },
    {
        "src": "music/Burial-Nightmarket.mp3",
        "trackName": "Burial - Nightmarket",
        "genre": "Dubstep",
        "album" : "Tunes 2011-2019",
        "rating": []
    },
    {
        "src": "music/Burial-NYC.mp3",
        "trackName": "Burial - NYC",
        "genre": "Dubstep",
        "album" : "Tunes 2011-2019",
        "rating": []
    },
    {
        "src": "music/Burial-Rival_dealer.mp3",
        "trackName": "Burial - Rival dealer",
        "genre": "Dubstep",
        "album" : "Tunes 2011-2019",
        "rating": []
    },
    {
        "src": "music/Burial-Rough_sleeper.mp3",
        "trackName": "Burial - Rough sleeper",
        "genre": "Dubstep",
        "album" : "Tunes 2011-2019",
        "rating": []
    },
    {
        "src": "music/Burial-State_forest.mp3",
        "trackName": "Burial - State forest",
        "genre": "Dubstep",
        "album" : "Tunes 2011-2019",
        "rating": []
    },
    {
        "src": "music/Burial-Stolen_dog.mp3",
        "trackName": "Burial - Stolen dog",
        "genre": "Dubstep",
        "album" : "Tunes 2011-2019",
        "rating": []
    },
    {
        "src": "music/Burial-Street_halo.mp3",
        "trackName": "Burial - Street halo",
        "genre": "Dubstep",
        "album" : "Tunes 2011-2019",
        "rating": []
    },
    {
        "src": "music/Burial-Subtemple.mp3",
        "trackName": "Burial - Subtemple",
        "genre": "Dubstep",
        "album" : "Tunes 2011-2019",
        "rating": []
    },
    {
        "src": "music/Burial-Truant.mp3",
        "trackName": "Burial - Truant",
        "genre": "Dubstep",
        "album" : "Tunes 2011-2019",
        "rating": []
    },
    {
        "src": "music/Burial-Young_death.mp3",
        "trackName": "Burial - Young death",
        "genre": "Dubstep",
        "album" : "Tunes 2011-2019",
        "rating": []
    },
    {
        "src": "music/Coldplay-Champion_of_the_world.mp3",
        "trackName": "Coldplay - Champion of the world",
        "genre": "Rock",
        "album" : "Everyday Life",
        "rating": []
    },
    {
        "src": "music/Coldplay-Arabesque.mp3",
        "trackName": "Coldplay - Arabesque",
        "genre": "Rock",
        "album" : "Everyday Life",
        "rating": []
    },
    {
        "src": "music/Coldplay-Bani_adam.mp3",
        "trackName": "Coldplay - Bani adam",
        "genre": "Rock",
        "album" : "Everyday Life",
        "rating": []
    },
    {
        "src": "music/Coldplay-brokEn.mp3",
        "trackName": "Coldplay - brokEn",
        "genre": "Rock",
        "album" : "Everyday Life",
        "rating": []
    },
    {
        "src": "music/Coldplay-Church.mp3",
        "trackName": "Coldplay - Church",
        "genre": "Rock",
        "album" : "Everyday Life",
        "rating": []
    },
    {
        "src": "music/Coldplay-cry_cry_cry.mp3",
        "trackName": "Coldplay - Cry Cry Cry",
        "genre": "Rock",
        "album" : "Everyday Life",
        "rating": []
    },
    {
        "src": "music/Coldplay-Daddy.mp3",
        "trackName": "Coldplay - Daddy",
        "genre": "Rock",
        "album" : "Everyday Life",
        "rating": []
    },
    {
        "src": "music/Coldplay-Eko.mp3",
        "trackName": "Coldplay - Eko",
        "genre": "Rock",
        "album" : "Everyday Life",
        "rating": []
    },
    {
        "src": "music/Coldplay-Everyday_life.mp3",
        "trackName": "Coldplay - Everyday life",
        "genre": "Rock",
        "album" : "Everyday Life",
        "rating": []
    },
    {
        "src": "music/Coldplay-guns.mp3",
        "trackName": "Coldplay - Guns",
        "genre": "Rock",
        "album" : "Everyday Life",
        "rating": []
    },
    {
        "src": "music/Coldplay-Old_friends.mp3",
        "trackName": "Coldplay - Friends",
        "genre": "Rock",
        "album" : "Everyday Life",
        "rating": []
    },
    {
        "src": "music/Coldplay-Orphans.mp3",
        "trackName": "Coldplay - Orphans",
        "genre": "Rock",
        "album" : "Everyday Life",
        "rating": []
    },
    {
        "src": "music/Coldplay-Sunrise.mp3",
        "trackName": "Coldplay - Sunrise",
        "genre": "Rock",
        "album" : "Everyday Life",
        "rating": []
    },
    {
        "src": "music/Coldplay-Trouble_town.mp3",
        "trackName": "Coldplay - Trouble town",
        "genre": "Rock",
        "album" : "Everyday Life",
        "rating": []
    },
    {
        "src": "music/Coldplay-when_i_need_a_friend.mp3",
        "trackName": "Coldplay - When i need a friend",
        "genre": "Rock",
        "album" : "Everyday Life",
        "rating": []
    },
    {
        "src": "music/Coldplay-WOTW.mp3",
        "trackName": "Coldplay - WOTW",
        "genre": "Rock",
        "album" : "Everyday Life",
        "rating": []
    },
    {
        "src": "music/DJ_20Shadow-Beauty_Power_Motion_Life_Work_Chaos_Law.mp3",
        "trackName": "DJ Shadow - Beauty, Power, Motion, Life, Work, Chaos, Law",
        "genre": "Hip-hop",
        "album" : "Our Pathetic Age",
        "rating": []
    },
    {
        "src": "music/DJ_Shadow-Firestorm.mp3",
        "trackName": "DJ Shadow - Firestorm",
        "genre": "Hip-hop",
        "album" : "Our Pathetic Age",
        "rating": []
    },
    {
        "src": "music/DJ_Shadow-I_Am_Not_A_Robot.mp3",
        "trackName": "DJ Shadow - I am not a robot",
        "genre": "Hip-hop",
        "album" : "Our Pathetic Age",
        "rating": []
    },
    {
        "src": "music/DJ_Shadow-If_I_Died_Today.mp3",
        "trackName": "DJ Shadow - If i died today",
        "genre": "Hip-hop",
        "album" : "Our Pathetic Age",
        "rating": []
    },
    {
        "src": "music/DJ_Shadow-Intersectionality.mp3",
        "trackName": "DJ Shadow - Intersectionality",
        "genre": "Hip-hop",
        "album" : "Our Pathetic Age",
        "rating": []
    },
    {
        "src": "music/DJ_Shadow-Juggernaut.mp3",
        "trackName": "DJ Shadow - Juggernaut",
        "genre": "Hip-hop",
        "album" : "Our Pathetic Age",
        "rating": []
    },
    {
        "src": "music/DJ_Shadow-My_Lonely_Room.mp3",
        "trackName": "DJ Shadow - Lonely Room",
        "genre": "Hip-hop",
        "album" : "Our Pathetic Age",
        "rating": []
    },
    {
        "src": "music/DJ_Shadow-Nature_Always_Wins.mp3",
        "trackName": "DJ Shadow - Nature always wins",
        "genre": "Hip-hop",
        "album" : "Our Pathetic Age",
        "rating": []
    },
    {
        "src": "music/DJ_Shadow-Rosie.mp3",
        "trackName": "DJ Shadow - Rosie",
        "genre": "Hip-hop",
        "album" : "Our Pathetic Age",
        "rating": []
    },
    {
        "src": "music/DJ_Shadow-Slingblade.mp3",
        "trackName": "DJ Shadow - Slingblade",
        "genre": "Hip-hop",
        "album" : "Our Pathetic Age",
        "rating": []
    },
    {
        "src": "music/DJ_Shadow-We_Are_Always_Alone.mp3",
        "trackName": "DJ Shadow - We are always alone",
        "genre": "Hip-hop",
        "album" : "Our Pathetic Age",
        "rating": []
    },
    {
        "src": "music/DJ_Shadow-Weightless.mp3",
        "trackName": "DJ Shadow - Weightless",
        "genre": "Hip-hop",
        "album" : "Our Pathetic Age",
        "rating": []
    },
    {
        "src": "music/DJ_Shadow_feat_Barny_Fletcher-Two_Notes.mp3",
        "trackName": "DJ Shadow - Two notes",
        "genre": "Hip-hop",
        "album" : "Our Pathetic Age",
        "rating": []
    },
    {
        "src": "music/DJ_Shadow_feat_Dave_East_Loyle_Carner-Taxin.mp3",
        "trackName": "DJ Shadow - Taxin'",
        "genre": "Hip-hop",
        "album" : "Our Pathetic Age",
        "rating": []
    },
    {
        "src": "music/DJ_Shadow_feat_De_La_Soul-Rocket_Fuel.mp3",
        "trackName": "DJ Shadow - Rocket Fuel",
        "genre": "Hip-hop",
        "album" : "Our Pathetic Age",
        "rating": []
    },
    {
        "src": "music/DJ_Shadow_feat_Fantastic_Negrito_Jumbo_is_Dr.ama-Dark_Side_Of_The_Heart.mp3",
        "trackName": "DJ Shadow - Dark side of the hearth",
        "genre": "Hip-hop",
        "album" : "Our Pathetic Age",
        "rating": []
    },
    {
        "src": "music/DJ_Shadow_feat_Gift_Of_Gab_Lateef_The_Truth_Speaker_Infamous_Taz-C.O.N.F.O.R.M..mp3",
        "trackName": "DJ Shadow - C.O.N.F.O.R.M.",
        "genre": "Hip-hop",
        "album" : "Our Pathetic Age",
        "rating": []
    },
    {
        "src": "music/DJ_Shadow_feat_Inspectah_Deck_Ghostface_Killah_Raekwon-Rain_On_Snow.mp3",
        "trackName": "DJ Shadow - Rain on snow",
        "genre": "Hip-hop",
        "album" : "Our Pathetic Age",
        "rating": []
    },
    {
        "src": "music/DJ_Shadow_feat_Nas_Pharoahe_Monch-Drone_Warfare.mp3",
        "trackName": "DJ Shadow - Drone Warfare",
        "genre": "Hip-hop",
        "album" : "Our Pathetic Age",
        "rating": []
    },
    {
        "src": "music/DJ_Shadow_feat_Pusha_T-Been_Use_Ta.mp3",
        "trackName": "DJ Shadow - Been use ta",
        "genre": "Hip-hop",
        "album" : "Our Pathetic Age",
        "rating": []
    },
    {
        "src": "music/DJ_Shadow_feat_Rockwell_Knuckles_Tef_Poe_Daemon-Urgent_Important_Please_Read.mp3",
        "trackName": "DJ Shadow - Urgent important please read",
        "genre": "Hip-hop",
        "album" : "Our Pathetic Age",
        "rating": []
    },
    {
        "src": "music/DJ_Shadow_feat_Run_The_Jewels-Kings_and_Queens.mp3",
        "trackName": "DJ Shadow - Kings&Queens",
        "genre": "Hip-hop",
        "album" : "Our Pathetic Age",
        "rating": []
    },
    {
        "src": "music/DJ_Shadow_feat_Samuel_T_Herring-Our_Pathetic_Age.mp3",
        "trackName": "DJ Shadow - Our pathetic age",
        "genre": "Hip-hop",
        "album" : "Our Pathetic Age",
        "rating": []
    },
    {
        "src": "music/DJ_Shadow_feat_Stro-JoJos_Word.mp3",
        "trackName": "DJ Shadow - Jojo's world",
        "genre": "Hip-hop",
        "album" : "Our Pathetic Age",
        "rating": []
    },
    {
        "src": "music/DJ_Shadow_feat_Wiki_Paul_Banks-Small_Colleges_Stay_With_Me.mp3",
        "trackName": "DJ Shadow - Small colleges stay with me",
        "genre": "Hip-hop",
        "album" : "Our Pathetic Age",
        "rating": []
    },
    {
        "src": "music/Gang_Starr-Bad_Name.mp3",
        "trackName": "Gang Starr - Bad Name",
        "genre": "Hip-hop",
        "album" : "One of the Best Yet",
        "rating": []
    },
    {
        "src": "music/Gang_Starr-Bless_The_Mic.mp3",
        "trackName": "Gang Starr - The mic",
        "genre": "Hip-hop",
        "album" : "One of the Best Yet",
        "rating": []
    },
    {
        "src": "music/Gang_Starr-Bring_It_Back_Here.mp3",
        "trackName": "Gang Starr - Bring it back here",
        "genre": "Hip-hop",
        "album" : "One of the Best Yet",
        "rating": []
    },
    {
        "src": "music/Gang_Starr-Keith_Casim_Elam_Interlude.mp3",
        "trackName": "Gang Starr - Keith casim elam",
        "genre": "Hip-hop",
        "album" : "One of the Best Yet",
        "rating": []
    },
    {
        "src": "music/Gang_Starr-NYGz_FGS_183rd_Interlude.mp3",
        "trackName": "Gang Starr - NYGz/GS 183rd",
        "genre": "Hip-hop",
        "album" : "One of the Best Yet",
        "rating": []
    },
    {
        "src": "music/Gang_Starr-One_Of_The_Best_Yet_Big_Shug_Interlude.mp3",
        "trackName": "Gang Starr - The best yet",
        "genre": "Hip-hop",
        "album" : "One of the Best Yet",
        "rating": []
    },
    {
        "src": "music/Gang_Starr-So_Many_Rappers.mp3",
        "trackName": "Gang Starr - So many rappers",
        "genre": "Hip-hop",
        "album" : "One of the Best Yet",
        "rating": []
    },
    {
        "src": "music/Gang_Starr-The_Sure_Shot_Intro.mp3",
        "trackName": "Gang Starr - The sure shot",
        "genre": "Hip-hop",
        "album" : "One of the Best Yet",
        "rating": []
    },
    {
        "src": "music/Gang_Starr_feat_Big_Shug_Freddie_Foxxx-Take_Flight_Militia_Pt_4.mp3",
        "trackName": "Gang Starr - Take flight",
        "genre": "Hip-hop",
        "album" : "One of the Best Yet",
        "rating": []
    },
    {
        "src": "music/Gang_Starr_feat_Group_Home_Royce_Da_5_9-Whats_Real.mp3",
        "trackName": "Gang Starr - What's real",
        "genre": "Hip-hop",
        "album" : "One of the Best Yet",
        "rating": []
    },
    {
        "src": "music/Gang_Starr_feat_J_Cole-Family_and_Loyalty.mp3",
        "trackName": "Gang Starr - Family and loyalty",
        "genre": "Hip-hop",
        "album" : "One of the Best Yet",
        "rating": []
    },
    {
        "src": "music/Gang_Starr_feat_Jeru_The_Damaja-From_A_Distance.mp3",
        "trackName": "Gang Starr - From distance",
        "genre": "Hip-hop",
        "album" : "One of the Best Yet",
        "rating": []
    },
    {
        "src": "music/Gang_Starr_feat_M.O.P.-Lights_Out.mp3",
        "trackName": "Gang Starr - Lights out",
        "genre": "Hip-hop",
        "album" : "One of the Best Yet",
        "rating": []
    },
    {
        "src": "music/Gang_Starr_feat_Ne-Yo_Nitty_Scott-Get_Together.mp3",
        "trackName": "Gang Starr - Get together",
        "genre": "Hip-hop",
        "album" : "One of the Best Yet",
        "rating": []
    },
    {
        "src": "music/Gang_Starr_feat_Q-Tip-Hit_Man.mp3",
        "trackName": "Gang Starr - Hit Man",
        "genre": "Hip-hop",
        "album" : "One of the Best Yet",
        "rating": []
    },
    {
        "src": "music/Gang_Starr_feat_Talib_Kweli-Business_Or_Art.mp3",
        "trackName": "Gang Starr - Business art",
        "genre": "Hip-hop",
        "album" : "One of the Best Yet",
        "rating": []
    },
    {
        "src": "music/Harry_styles-Adore_you.mp3",
        "trackName": "Harry Styles - Adore you",
        "genre": "Pop",
        "album" : "Fine Line",
        "rating": []
    },
    {
        "src": "music/Harry_styles-Canyon_moon.mp3",
        "trackName": "Harry Styles - Canyon moon",
        "genre": "Pop",
        "rating": []
    },
    {
        "src": "music/Harry_styles-Cherry.mp3",
        "trackName": "Harry Styles - Cherry",
        "genre": "Pop",
        "album" : "Fine Line",
        "rating": []
    },
    {
        "src": "music/Harry_styles-She.mp3",
        "trackName": "Harry Styles - She",
        "genre": "Pop",
        "album" : "Fine Line",
        "rating": []
    },
    {
        "src": "music/Harry_styles-Falling.mp3",
        "trackName": "Harry Styles - Falling",
        "genre": "Pop",
        "album" : "Fine Line",
        "rating": []
    },
    {
        "src": "music/Harry_Styles-Fine_line.mp3",
        "trackName": "Harry Styles - Fine line",
        "genre": "Pop",
        "album" : "Fine Line",
        "rating": []
    },
    {
        "src": "music/Harry_Styles-Golden.mp3",
        "trackName": "Harry Styles - Golden",
        "genre": "Pop",
        "album" : "Fine Line",
        "rating": []
    },
    {
        "src": "music/Harry_Styles-Lights_up.mp3",
        "trackName": "Harry Styles - Lights",
        "genre": "Pop",
        "album" : "Fine Line",
        "rating": []
    },
    {
        "src": "music/Harry_Styles-Sunflower_vol_6.mp3",
        "trackName": "Harry Styles - Sunflower",
        "genre": "Pop",
        "album" : "Fine Line",
        "rating": []
    },
    {
        "src": "music/Harry_Styles-To_be_so_lonely.mp3",
        "trackName": "Harry Styles- To be so lonely",
        "genre": "Pop",
        "album" : "Fine Line",
        "rating": []
    },
    {
        "src": "music/Harry_Styles-Treat_people_with_kindness.mp3",
        "trackName": "Harry Styles - Treat people with kindness",
        "genre": "Pop",
        "album" : "Fine Line",
        "rating": []
    },
    {
        "src": "music/Harry_Styles-Watermelon_sugar.mp3",
        "trackName": "Harry Styles - Watermelon sugar",
        "genre": "Pop",
        "album" : "Fine Line",
        "rating": []
    },
    {
        "src": "music/Leonard_Cohen-the_goal.mp3",
        "trackName": "Leonard Cohen - Cohen the goal",
        "genre": "Rock",
        "album" : "Thanks for the Dance",
        "rating": []
    },
    {
        "src": "music/Leonard_Cohen-Happens_to_the_Heart.mp3",
        "trackName": "Leonard Cohen - Happens to the heart",
        "genre": "Rock",
        "album" : "Thanks for the Dance",
        "rating": []
    },
    {
        "src": "music/Leonard_Cohen-Listen_to_the_Hummingbird.mp3",
        "trackName": "Leonard Cohen - Listen to the Hummingbird",
        "genre": "Rock",
        "album" : "Thanks for the Dance",
        "rating": []
    },
    {
        "src": "music/Leonard_Cohen-Moving-on.mp3",
        "trackName": "Leonard Cohen - Moving-on",
        "genre": "Rock",
        "album" : "Thanks for the Dance",
        "rating": []
    },
    {
        "src": "music/Leonard_Cohen-Puppets.mp3",
        "trackName": "Leonard Cohen - Puppets",
        "genre": "Rock",
        "album" : "Thanks for the Dance",
        "rating": []
    },
    {
        "src": "music/Leonard_Cohen-Thanks_for_dance.mp3",
        "trackName": "Leonard Cohen - Thanks for dance",
        "genre": "Rock",
        "album" : "Thanks for the Dance",
        "rating": []
    },
    {
        "src": "music/Leonard_Cohen-The_Hills.mp3",
        "trackName": "Leonard Cohen - The hills",
        "genre": "Rock",
        "album" : "Thanks for the Dance",
        "rating": []
    },
    {
        "src": "music/Liam_Payne-Bedroom_floor.mp3",
        "trackName": "Liam Payne - Bedroom floor",
        "genre": "Pop",
        "album" : "LP1",
        "rating": []
    },
    {
        "src": "music/Liam_Payne-All_i_want .mp3",
        "trackName": "Liam Payne - All i want",
        "genre": "Pop",
        "album" : "LP1",
        "rating": []
    },
    {
        "src": "music/Liam_Payne-Both_ways.mp3",
        "trackName": "Liam Payne - Both ways",
        "genre": "Pop",
        "album" : "LP1",
        "rating": []
    },
    {
        "src": "music/Liam_Payne-Familiar.mp3",
        "trackName": "Liam Payne - Familiar",
        "genre": "Pop",
        "album" : "LP1",
        "rating": []
    },
    {
        "src": "music/Liam_Payne-For_you.mp3",
        "trackName": "Liam Payne - For you",
        "genre": "Pop",
        "album" : "LP1",
        "rating": []
    },
    {
        "src": "music/Liam_Payne-Get_low.mp3",
        "trackName": "Liam Payne - Get low",
        "genre": "Pop",
        "album" : "LP1",
        "rating": []
    },
    {
        "src": "music/Liam_Payne-Hips_dont_lie.mp3",
        "trackName": "Liam Payne - Hips don't lie",
        "genre": "Pop",
        "album" : "LP1",
        "rating": []
    },
    {
        "src": "music/Liam_Payne-Live_forever.mp3",
        "trackName": "Liam Payne - Live forever",
        "genre": "Pop",
        "album" : "LP1",
        "rating": []
    },
    {
        "src": "music/Liam_Payne-Polaroid.mp3",
        "trackName": "Liam Payne - Polaroid",
        "genre": "Pop",
        "album" : "LP1",
        "rating": []
    },
    {
        "src": "music/Liam_Payne-Remember.mp3",
        "trackName": "Liam Payne - Remember",
        "genre": "Pop",
        "album" : "LP1",
        "rating": []
    },
    {
        "src": "music/Liam_Payne-Rude_hours.mp3",
        "trackName": "Liam Payne - Rude hours",
        "genre": "Pop",
        "album" : "LP1",
        "rating": []
    },
    {
        "src": "music/Liam_Payne-Say_it_all.mp3",
        "trackName": "Liam Payne - Say it all",
        "genre": "Pop",
        "album" : "LP1",
        "rating": []
    },
    {
        "src": "music/Liam_Payne-Stack_it_up.mp3",
        "trackName": "Liam Payne - Stack it up",
        "genre": "Pop",
        "album" : "LP1",
        "rating": []
    },
    {
        "src": "music/Liam_Payne-Strip_that_down.mp3",
        "trackName": "Liam Payne - Strip that down",
        "genre": "Pop",
        "album" : "LP1",
        "rating": []
    },
    {
        "src": "music/Liam_Payne-Tell_your_friends.mp3",
        "trackName": "Liam Payne - Tell your friends",
        "genre": "Pop",
        "album" : "LP1",
        "rating": []
    },
    {
        "src": "music/Liam_Payne-Weekend.mp3",
        "trackName": "Liam Payne - Weekend",
        "genre": "Pop",
        "album" : "LP1",
        "rating": []
    },
    {
        "src": "music/Lil_Peep-White_tee.mp3",
        "trackName": "Lil Peep - White tee",
        "genre": "Hip-hop",
        "album" : "Everybody's Everything",
        "rating": []
    },
    {
        "src": "music/Lil_Peep-Belgium.mp3",
        "trackName": "Lil Peep - Belgium",
        "genre": "Hip-hop",
        "album" : "Everybody's Everything",
        "rating": []
    },
    {
        "src": "music/Lil_Peep-Ghost_boy.mp3",
        "trackName": "Lil Peep - Ghost boy",
        "genre": "Hip-hop",
        "album" : "Everybody's Everything",
        "rating": []
    },
    {
        "src": "music/Lil_Peep-Keep_my_Coo.mp3",
        "trackName": "Lil Peep - Keep my Coo",
        "genre": "Hip-hop",
        "album" : "Everybody's Everything",
        "rating": []
    },
    {
        "src": "music/Lil_Peep-Liar.mp3",
        "trackName": "Lil Peep - Liar",
        "genre": "Hip-hop",
        "album" : "Everybody's Everything",
        "rating": []
    },
    {
        "src": "music/Lil_Peep-Live_Forever.mp3",
        "trackName": "Lil Peep - Live forever",
        "genre": "Hip-hop",
        "album" : "Everybody's Everything",
        "rating": []
    },
    {
        "src": "music/Lil_Peep-Moving_On.mp3",
        "trackName": "Lil Peep - Moving on",
        "genre": "Hip-hop",
        "album" : "Everybody's Everything",
        "rating": []
    },
    {
        "src": "music/Lil_Peep-PRINCESS.mp3",
        "trackName": "Lil Peep - PRINCESS",
        "genre": "Hip-hop",
        "album" : "Everybody's Everything",
        "rating": []
    },
    {
        "src": "music/Lil_Peep-RATCHETS.mp3",
        "trackName": "Lil Peep - RATCHETS",
        "genre": "Hip-hop",
        "album" : "Everybody's Everything",
        "rating": []
    },
    {
        "src": "music/Lil_Peep-When_i_Lie.mp3",
        "trackName": "Lil Peep - When i lie",
        "genre": "Hip-hop",
        "album" : "Everybody's Everything",
        "rating": []
    },
    {
        "src": "music/Lil_Peep-Witchblades.mp3",
        "trackName": "Lil Peep - Witchblades",
        "genre": "Hip-hop",
        "album" : "Everybody's Everything",
        "rating": []
    },
    {
        "src": "music/Lil_Peep-Cobain.mp3",
        "trackName": "Lil Peep - Cobain",
        "genre": "Hip-hop",
        "album" : "Everybody's Everything",
        "rating": []
    },
    {
        "src": "music/Lil_Peep_feat_Era-Text_Me.mp3",
        "trackName": "Lil Peep - Text me",
        "genre": "Hip-hop",
        "album" : "Everybody's Everything",
        "rating": []
    },
    {
        "src": "music/Lil_Peep_feat_Gab-Fangirl.mp3",
        "trackName": "Lil Peep - Fangirl",
        "genre": "Hip-hop",
        "album" : "Everybody's Everything",
        "rating": []
    },
    {
        "src": "music/Lil_Peep_feat_Gab-LA_to_London.mp3",
        "trackName": "Lil Peep - LA to London",
        "genre": "Hip-hop",
        "album" : "Everybody's Everything",
        "rating": []
    },
    {
        "src": "music/Lil_Peep_feat_Gab3-Rockstarz.mp3",
        "trackName": "Lil Peep - Rockstarz",
        "genre": "Hip-hop",
        "rating": []
    },
    {
        "src": "music/Lil_Peep_feat_ILOVEMAKONNEN-Ive_Been_Waiting.mp3",
        "trackName": "Lil Peep - I've been waiting",
        "genre": "Hip-hop",
        "album" : "Everybody's Everything",
        "rating": []
    },
    {
        "src": "music/Lil_Peep_feat_Rich_The_Kid-AQUAFINA.mp3",
        "trackName": "Lil Peep - AQUAFINA",
        "genre": "Hip-hop",
        "album" : "Everybody's Everything",
        "rating": []
    },
    {
        "src": "music/Lil_Peep-Walk_away_as_the_door_slams.mp3",
        "trackName": "Lil Peep - Walk away as the door slams",
        "genre": "Hip-hop",
        "album" : "Everybody's Everything",
        "rating": []
    },
    {
        "src": "music/Luke_Combs_Brooks_Dunn-1_2_Many.mp3",
        "trackName": "Luke Combs - 1 2 many",
        "genre": "Country",
        "album" : "What You See Is What You Get",
        "rating": []
    },
    {
        "src": "music/Luke_Combs-All_Over_Again.mp3",
        "trackName": "Luke Combs - All over again",
        "genre": "Country",
        "album" : "What You See Is What You Get",
        "rating": []
    },
    {
        "src": "music/Luke_Combs-Angels_Workin_Overtime.mp3",
        "trackName": "Luke Combs - Angels workin overtime",
        "genre": "Country",
        "album" : "What You See Is What You Get",
        "rating": []
    },
    {
        "src": "music/Luke_Combs-Beer_Never_Broke_My_Heart.mp3",
        "trackName": "Luke Combs - Beer never broke my heart",
        "genre": "Country",
        "album" : "What You See Is What You Get",
        "rating": []
    },
    {
        "src": "music/Luke_Combs-Better_Together.mp3",
        "trackName": "Luke Combs - Better together",
        "genre": "Country",
        "album" : "What You See Is What You Get",
        "rating": []
    },
    {
        "src": "music/Luke_Combs-Blue_Collar_Boys.mp3",
        "trackName": "Luke Combs - Blue collar boys",
        "genre": "Country",
        "album" : "What You See Is What You Get",
        "rating": []
    },
    {
        "src": "music/Luke_Combs-Dear_Today.mp3",
        "trackName": "Luke Combs - Dear today",
        "genre": "Country",
        "album" : "What You See Is What You Get",
        "rating": []
    },
    {
        "src": "music/Luke_Combs-Even_Though_Im_Leaving.mp3",
        "trackName": "Luke Combs - Even though i'm leaving",
        "genre": "Country",
        "album" : "What You See Is What You Get",
        "rating": []
    },
    {
        "src": "music/Luke_Combs-Every_Little_Bit_Helps.mp3",
        "trackName": "Luke Combs - Every little bit helps",
        "genre": "Country",
        "album" : "What You See Is What You Get",
        "rating": []
    },
    {
        "src": "music/Luke_Combs-Lovin_On_You.mp3",
        "trackName": "Luke Combs - Lovin on you",
        "genre": "Country",
        "album" : "What You See Is What You Get",
        "rating": []
    },
    {
        "src": "music/Luke_Combs-Moon_Over_Mexico.mp3",
        "trackName": "Luke Combs - Moon over Mexico",
        "genre": "Country",
        "album" : "What You See Is What You Get",
        "rating": []
    },
    {
        "src": "music/Luke_Combs-New_Every_Day.mp3",
        "trackName": "Luke Combs - New every day",
        "genre": "Country",
        "album" : "What You See Is What You Get",
        "rating": []
    },
    {
        "src": "music/Luke_Combs-Nothing_Like_You.mp3",
        "trackName": "Luke Combs - Nothing like you",
        "genre": "Country",
        "album" : "What You See Is What You Get",
        "rating": []
    },
    {
        "src": "music/Luke_Combs-Reasons.mp3",
        "trackName": "Luke Combs - Reasons",
        "genre": "Country",
        "album" : "What You See Is What You Get",
        "rating": []
    },
    {
        "src": "music/Luke_Combs-Refrigerator_Door.mp3",
        "trackName": "Luke Combs - Refrigerator door",
        "genre": "Country",
        "album" : "What You See Is What You Get",
        "rating": []
    },
    {
        "src": "music/Luke_Combs-What_You_See_Is_What_You_Get.mp3",
        "trackName": "Luke Combs - What you see is what you get",
        "genre": "Country",
        "album" : "What You See Is What You Get",
        "rating": []
    },
    {
        "src": "music/Luke_Combs_feat_Eric_Church-Does_To_Me.mp3",
        "trackName": "Luke Combs - Does to me",
        "genre": "Country",
        "album" : "What You See Is What You Get",
        "rating": []
    },
    {
        "src": "music/Robbie_Williams-Best_Christmas_Ever.mp3",
        "trackName": "Robbie Williams - Best Christmas ever",
        "genre": "Pop",
        "album" : "The Christmas Present",
        "rating": []
    },
    {
        "src": "music/Robbie_Williams-Coco_Christmas.mp3",
        "trackName": "Robbie Williams - Coco Christmas",
        "genre": "Pop",
        "album" : "The Christmas Present",
        "rating": []
    },
    {
        "src": "music/Robbie_Williams-Coco_Christmas_Lullaby.mp3",
        "trackName": "Robbie Williams - Coco 27's Christmas Lullaby",
        "genre": "Pop",
        "album" : "The Christmas Present",
        "rating": []
    },
    {
        "src": "music/Robbie_Williams-Coco_Christmas_Lullaby_Reprise.mp3",
        "trackName": "Robbie Williams - Coco 27's Christmas Lullaby Reprise",
        "genre": "Pop",
        "album" : "The Christmas Present",
        "rating": []
    },
    {
        "src": "music/Robbie_Williams-Darkest_Night.mp3",
        "trackName": "Robbie Williams - Darkest Night",
        "genre": "Pop",
        "album" : "The Christmas Present",
        "rating": []
    },
    {
        "src": "music/Robbie_Williams-Happy_Birthday_Jesus_Christ.mp3",
        "trackName": "Robbie Williams - Happy birthday Jesus Christ",
        "genre": "Pop",
        "album" : "The Christmas Present",
        "rating": []
    },
    {
        "src": "music/Robbie_Williams-Home.mp3",
        "trackName": "Robbie Williams - Home",
        "genre": "Pop",
        "album" : "The Christmas Present",
        "rating": []
    },
    {
        "src": "music/Robbie_Williams-Idlewild.mp3",
        "trackName": "Robbie Williams - Idlewild",
        "genre": "Pop",
        "album" : "The Christmas Present",
        "rating": []
    },
    {
        "src": "music/Robbie_Williams-Let_It_snow.mp3",
        "trackName": "Robbie Williams - Let it snow",
        "genre": "Pop",
        "album" : "The Christmas Present",
        "rating": []
    },
    {
        "src": "music/Robbie_Williams-Let_Not_Go_Shopping.mp3",
        "trackName": "Robbie Williams - Let's not go shopping",
        "genre": "Pop",
        "album" : "The Christmas Present",
        "rating": []
    },
    {
        "src": "music/Robbie_Williams-Merry_Xmas_everybody.mp3",
        "trackName": "Robbie Williams - Merry Xmas everbody",
        "genre": "Pop",
        "album" : "The Christmas Present",
        "rating": []
    },
    {
        "src": "music/Robbie_Williams-New_Year_Day.mp3",
        "trackName": "Robbie Williams - New year's day",
        "genre": "Pop",
        "album" : "The Christmas Present",
        "rating": []
    },
    {
        "src": "music/Robbie_Williams-One_Last_Christmas.mp3",
        "trackName": "Robbie Williams - One last Christmas",
        "genre": "Pop",
        "album" : "The Christmas Present",
        "rating": []
    },
    {
        "src": "music/Robbie_Williams-Rudolph.mp3",
        "trackName": "Robbie Williams - Rudolph",
        "genre": "Pop",
        "album" : "The Christmas Present",
        "rating": []
    },
    {
        "src": "music/Robbie_Williams-Snowflakes.mp3",
        "trackName": "Robbie Williams - Snowflakes",
        "genre": "Pop",
        "album" : "The Christmas Present",
        "rating": []
    },
    {
        "src": "music/Robbie_Williams-Soul_Transmission.mp3",
        "trackName": "Robbie Williams - Soul transmission",
        "genre": "Pop",
        "album" : "The Christmas Present",
        "rating": []
    },
    {
        "src": "music/Robbie_Williams-The_Christmas_Song.mp3",
        "trackName": "Robbie Williams - The Christmas song",
        "genre": "Pop",
        "album" : "The Christmas Present",
        "rating": []
    },
    {
        "src": "music/Robbie_Williams-Winter_wonderland.mp3",
        "trackName": "Robbie Williams - Winter wonderland",
        "genre": "Pop",
        "album" : "The Christmas Present",
        "rating": []
    },
    {
        "src": "music/Robbie_Williams-Yeah_Its_Christmas.mp3",
        "trackName": "Robbie Williams - Yeah it's Christmas",
        "genre": "Pop",
        "album" : "The Christmas Present",
        "rating": []
    },
    {
        "src": "music/Robbie-Williams_feat_Bryan_Adams-Christmas.mp3",
        "trackName": "Robbie Williams - Christmas",
        "genre": "Pop",
        "album" : "The Christmas Present",
        "rating": []
    },
    {
        "src": "music/Robbie_Williams_feat_Helene_Fischer-Santa_Baby.mp3",
        "trackName": "Robbie Williams - Santa baby",
        "genre": "Pop",
        "album" : "The Christmas Present",
        "rating": []
    },
    {
        "src": "music/Robbie_Williams_feat_Poppa_Pete-Its_a_Wonderful_Life.mp3",
        "trackName": "Robbie Williams - It's wonderful life",
        "genre": "Pop",
        "album" : "The Christmas Present",
        "rating": []
    },
    {
        "src": "music/Robbie_Williams_feat_RodStewart-Fairytales.mp3",
        "trackName": "Robbie Williams - Fairytales",
        "genre": "Pop",
        "album" : "The Christmas Present",
        "rating": []
    },
    {
        "src": "music/Robbie_Williams_feat_Tyson_Fury-Bad_Sharon.mp3",
        "trackName": "Robbie Williams - Bad sharon",
        "genre": "Pop",
        "album" : "The Christmas Present",
        "rating": []
    },
    {
        "src": "music/Robbie_Williams-Time_for_Change.mp3",
        "trackName": "Robbie Williams - Time for change",
        "genre": "Pop",
        "album" : "The Christmas Present",
        "rating": []
    },
    {
        "src": "music/Stormzy-Audacity.mp3",
        "trackName": "Stormzy - Audacity",
        "genre": "Hip-hop",
        "album" : "Heavy Is the Head",
        "rating": []
    },
    {
        "src": "music/Stormzy-Big_michael.mp3",
        "trackName": "Stormzy - Big michael",
        "genre": "Hip-hop",
        "album" : "Heavy Is the Head",
        "rating": []
    },
    {
        "src": "music/Stormzy-Bronze.mp3",
        "trackName": "Stormzy - Bronze",
        "genre": "Hip-hop",
        "album" : "Heavy Is the Head",
        "rating": []
    },
    {
        "src": "music/Stormzy-Crown.mp3",
        "trackName": "Stormzy - Crown",
        "genre": "Hip-hop",
        "album" : "Heavy Is the Head",
        "rating": []
    },
    {
        "src": "music/Stormzy-Do_better.mp3",
        "trackName": "Stormzy - Do better",
        "genre": "Hip-hop",
        "album" : "Heavy Is the Head",
        "rating": []
    },
    {
        "src": "music/Stormzy-Dont_forget_to_breathe.mp3",
        "trackName": "Stormzy - Dont forget to breathe",
        "genre": "Hip-hop",
        "album" : "Heavy Is the Head",
        "rating": []
    },
    {
        "src": "music/Stormzy-Handsome.mp3",
        "trackName": "Stormzy - Handsome",
        "genre": "Hip-hop",
        "album" : "Heavy Is the Head",
        "rating": []
    },
    {
        "src": "music/Stormzy-Lessons.mp3",
        "trackName": "Stormzy - Lessons",
        "genre": "Hip-hop",
        "album" : "Heavy Is the Head",
        "rating": []
    },
    {
        "src": "music/Stormzy-One_second.mp3",
        "trackName": "Stormzy - One second",
        "genre": "Hip-hop",
        "album" : "Heavy Is the Head",
        "rating": []
    },
    {
        "src": "music/Stormzy-Own_it.mp3",
        "trackName": "Stormzy - Own it",
        "genre": "Hip-hop",
        "album" : "Heavy Is the Head",
        "rating": []
    },
    {
        "src": "music/Stormzy-Pop_boy.mp3",
        "trackName": "Stormzy - Pop boy",
        "genre": "Hip-hop",
        "album" : "Heavy Is the Head",
        "rating": []
    },
    {
        "src": "music/Stormzy-Rachaels_little_brother.mp3",
        "trackName": "Stormzy - Rachel's little brother",
        "genre": "Hip-hop",
        "album" : "Heavy Is the Head",
        "rating": []
    },
    {
        "src": "music/Stormzy-Rainfall.mp3",
        "trackName": "Stormzy - Rainfall",
        "genre": "Hip-hop",
        "album" : "Heavy Is the Head",
        "rating": []
    },
    {
        "src": "music/Stormzy-Superheroes.mp3",
        "trackName": "Stormzy - Superheroes",
        "genre": "Hip-hop",
        "album" : "Heavy Is the Head",
        "rating": []
    },
    {
        "src": "music/Stormzy-Vossi_bop.mp3",
        "trackName": "Stormzy - Vossi bop",
        "genre": "Hip-hop",
        "album" : "Heavy Is the Head",
        "rating": []
    },
    {
        "src": "music/Stormzy-Wiley_flow.mp3",
        "trackName": "Stormzy - Wiley flow",
        "genre": "Hip-hop",
        "album" : "Heavy Is the Head",
        "rating": []
    },
    {
        "src": "music/Tory_Lanez_T-Pain-Jerry_Sprunger.mp3",
        "trackName": "Tory Lanez - Jerry Sprunger",
        "genre": "Hip-hop",
        "album" : "Chixtape5",
        "rating": []
    },
    {
        "src": "music/Tory_Lanez-Blowin_Mine_Leah_Introduction.mp3",
        "trackName": "Tory Lanez - Lowin mine",
        "genre": "Hip-hop",
        "album" : "Chixtape5",
        "rating": []
    },
    {
        "src": "music/Tory_Lanez-Broken_Promises.mp3",
        "trackName": "Tory Lanez - Broken promises",
        "genre": "Hip-hop",
        "album" : "Chixtape5",
        "rating": []
    },
    {
        "src": "music/Tory_Lanez-Jalissas_Back.mp3",
        "trackName": "Tory Lanez - Jalissa's back",
        "genre": "Hip-hop",
        "album" : "Chixtape5",
        "rating": []
    },
    {
        "src": "music/Tory_Lanez-Last_Love_Letter.mp3",
        "trackName": "Tory Lanez - Last love letter",
        "genre": "Hip-hop",
        "album" : "Chixtape5",
        "rating": []
    },
    {
        "src": "music/Tory_Lanez-Yessirr.mp3",
        "trackName": "Tory Lanez - Yessirr",
        "genre": "Hip-hop",
        "album" : "Chixtape5",
        "rating": []
    },
    {
        "src": "music/Tory_Lanez_feat_Ashanti-A_Fools_Tale_Running_Back.mp3",
        "trackName": "Tory Lanez - A fools tale running back",
        "genre": "Hip-hop",
        "album" : "Chixtape5",
        "rating": []
    },
    {
        "src": "music/Tory_Lanez_feat_Chris_Brown-The_Take.mp3",
        "trackName": "Tory Lanez - The take",
        "genre": "Hip-hop",
        "album" : "Chixtape5",
        "rating": []
    },
    {
        "src": "music/Tory_Lanez_featFabolous-If_You_Gotta.mp3",
        "trackName": "Tory Lanez - If you gotta...",
        "genre": "Hip-hop",
        "album" : "Chixtape5",
        "rating": []
    },
    {
        "src": "music/Tory_Lanez_feat_Jagged_Edge_Jermaine_Dupri-The_Trade.mp3",
        "trackName": "Tory Lanez - The trade",
        "genre": "Hip-hop",
        "album" : "Chixtape5",
        "rating": []
    },
    {
        "src": "music/Tory_Lanez_feat_Lloyd_Lil_Wayne-Thoughts.mp3",
        "trackName": "Tory Lanez - Thoughts",
        "genre": "Hip-hop",
        "album" : "Chixtape5",
        "rating": []
    },
    {
        "src": "music/Tory-Lanez-feat_Ludacris-The_Fargo_Splash.mp3",
        "trackName": "Tory Lanez - Fargo splash",
        "genre": "Hip-hop",
        "album" : "Chixtape5",
        "rating": []
    },
    {
        "src": "music/Tory_Lanez_feat_Mario-The_Cry.mp3",
        "trackName": "Tory Lanez - The cry",
        "genre": "Hip-hop",
        "album" : "Chixtape5",
        "rating": []
    },
    {
        "src": "music/Tory_Lanez_feat_Mya-Best_Of_You_Busted.mp3",
        "trackName": "Tory Lanez - Best of you",
        "genre": "Hip-hop",
        "album" : "Chixtape5",
        "rating": []
    },
    {
        "src": "music/Tory_Lanez_feat_Slim_Nyce-Room_112.mp3",
        "trackName": "Tory Lanez - Room 112",
        "genre": "Hip-hop",
        "album" : "Chixtape5",
        "rating": []
    },
    {
        "src": "music/Tory_Lanez_feat_Snoop_Dogg-Beauty_In_The_Benz.mp3",
        "trackName": "Tory Lanez - Beauty in the benz",
        "genre": "Hip-hop",
        "album" : "Chixtape5",
        "rating": []
    },
    {
        "src": "music/Tory_Lanez_feat_The-Dream-Luv_Ya_Gyal_Love_Sounds.mp3",
        "trackName": "Tory Lanez - Luv ya gyal",
        "genre": "Hip-hop",
        "album" : "Chixtape5",
        "rating": []
    },
    {
        "src": "music/Tory_Lanez_feat_Trey_Songz-Still_Waiting.mp3",
        "trackName": "Tory Lanez - Still waiting",
        "genre": "Hip-hop",
        "album" : "Chixtape5",
        "rating": []
    },
    {
        "src": "music/Trippie_redd-Bust_down.mp3",
        "trackName": "Trippie Redd - Bust down",
        "genre": "Hip-hop",
        "album" : "A Love Letter to You 4",
        "rating": []
    },
    {
        "src": "music/Trippie_redd-Can_you_rap_like_me.mp3",
        "trackName": "Trippie Redd - Can you rap like me",
        "genre": "Hip-hop",
        "album" : "A Love Letter to You 4",
        "rating": []
    },
    {
        "src": "music/Trippie_Redd-Abandoned.mp3",
        "trackName": "Trippie Redd - Abandoned",
        "genre": "Hip-hop",
        "album" : "A Love Letter to You 4",
        "rating": []
    },
    {
        "src": "music/Trippie_Redd-Bourne.mp3",
        "trackName": "Trippie Redd - Bourne",
        "genre": "Hip-hop",
        "album" : "A Love Letter to You 4",
        "rating": []
    },
    {
        "src": "music/Trippie_Redd-Death.mp3",
        "trackName": "Trippie Redd - Death",
        "genre": "Hip-hop",
        "album" : "A Love Letter to You 4",
        "rating": []
    },
    {
        "src": "music/Trippie_Redd-For_me.mp3",
        "trackName": "Trippie Redd - For me",
        "genre": "Hip-hop",
        "album" : "A Love Letter to You 4",
        "rating": []
    },
    {
        "src": "music/Trippie_Redd-Hate_me.mp3",
        "trackName": "Trippie Redd - Hate me",
        "genre": "Hip-hop",
        "album" : "A Love Letter to You 4",
        "rating": []
    },
    {
        "src": "music/Trippie_Redd-Leray.mp3",
        "trackName": "Trippie Redd - Leray",
        "genre": "Hip-hop",
        "album" : "A Love Letter to You 4",
        "rating": []
    },
    {
        "src": "music/Trippie_Redd-Love_me_more.mp3",
        "trackName": "Trippie Redd - Love me more",
        "genre": "Hip-hop",
        "album" : "A Love Letter to You 4",
        "rating": []
    },
    {
        "src": "music/Trippie_Redd-Love_sick.mp3",
        "trackName": "Trippie Redd - Love sick",
        "genre": "Hip-hop",
        "album" : "A Love Letter to You 4",
        "rating": []
    },
    {
        "src": "music/Trippie_Redd-Melly_kiss.mp3",
        "trackName": "Trippie Redd - Melly kiss",
        "genre": "Hip-hop",
        "album" : "A Love Letter to You 4",
        "rating": []
    },
    {
        "src": "music/Trippie_Redd-Real_feel.mp3",
        "trackName": "Trippie Redd - Real feel",
        "genre": "Hip-hop",
        "album" : "A Love Letter to You 4",
        "rating": []
    },
    {
        "src": "music/Trippie_Redd-RMP.mp3",
        "trackName": "Trippie Redd - RMP",
        "genre": "Hip-hop",
        "album" : "A Love Letter to You 4",
        "rating": []
    },
    {
        "src": "music/Trippie_Redd-Sickening.mp3",
        "trackName": "Trippie Redd - Sickening",
        "genre": "Hip-hop",
        "album" : "A Love Letter to You 4",
        "rating": []
    },
    {
        "src": "music/Trippie_Redd-The_grinch.mp3",
        "trackName": "Trippie Redd - The grinch",
        "genre": "Hip-hop",
        "album" : "A Love Letter to You 4",
        "rating": []
    },
    {
        "src": "music/Trippie_Redd-The_jungle_book.mp3",
        "trackName": "Trippie Redd - The jungle book",
        "genre": "Hip-hop",
        "album" : "A Love Letter to You 4",
        "rating": []
    },
    {
        "src": "music/Trippie_Redd-this_ain_that.mp3",
        "trackName": "Trippie Redd - This ain that",
        "genre": "Hip-hop",
        "album" : "A Love Letter to You 4",
        "rating": []
    },
    {
        "src": "music/Trippie_Redd-Til_the_end_of_time.mp3",
        "trackName": "Trippie Redd - Till the end of time",
        "genre": "Hip-hop",
        "album" : "A Love Letter to You 4",
        "rating": []
    },
    {
        "src": "music/Trippie_Redd-U_deserve_it.mp3",
        "trackName": "Trippie Redd - U deserve it",
        "genre": "Hip-hop",
        "album" : "A Love Letter to You 4",
        "rating": []
    },
    {
        "src": "music/Trippie_Redd-Who_needs_love.mp3",
        "trackName": "Trippie Redd - Who needs love",
        "genre": "Hip-hop",
        "album" : "A Love Letter to You 4",
        "rating": []
    },
    {
        "src": "music/Trippie_redd-Chosen.mp3",
        "trackName": "Trippie Redd - Chosen",
        "genre": "Hip-hop",
        "album" : "A Love Letter to You 4",
        "rating": []
    },
    {
        "src": "music/Will_Oldham-Big_Balls.mp3",
        "trackName": "Will Oldham - Big balls",
        "genre": "Country",
        "album" : "I made a place",
        "rating": []
    },
    {
        "src": "music/Will_Oldham-Boy_Have_You_Cum.mp3",
        "trackName": "Will Oldham - Boy have you cum",
        "genre": "Country",
        "album" : "I made a place",
        "rating": []
    },
    {
        "src": "music/Will_Oldham-Gezundheit.mp3",
        "trackName": "Will Oldham - Gezundheit",
        "genre": "Country",
        "album" : "I made a place",
        "rating": []
    },
    {
        "src": "music/Will_Oldham-I_See_a_Darkness.mp3",
        "trackName": "Will Oldham - I see a darkness",
        "genre": "Country",
        "album" : "I made a place",
        "rating": []
    },
    {
        "src": "music/Will_Oldham-Most_People.mp3",
        "trackName": "Will Oldham - Most people",
        "genre": "Country",
        "album" : "I made a place",
        "rating": []
    },
    {
        "src": "music/Will_Oldham-My_Only_Friend.mp3",
        "trackName": "Will Oldham - My only friend",
        "genre": "Country",
        "album" : "I made a place",
        "rating": []
    },
    {
        "src": "music/Will_Oldham-New_Partner.mp3",
        "trackName": "Will Oldham - New partner",
        "genre": "Country",
        "album" : "I made a place",
        "rating": []
    },
    {
        "src": "music/Will_Oldham-Only_Someone_Running.mp3",
        "trackName": "Will Oldham - Only someone running",
        "genre": "Country",
        "album" : "I made a place",
        "rating": []
    },
    {
        "src": "music/Will_Oldham-Patience.mp3",
        "trackName": "Will Oldham - Patience",
        "genre": "Country",
        "album" : "I made a place",
        "rating": []
    },
    {
        "src": "music/Will_Oldham-So_Far_And_Here_We_Are.mp3",
        "trackName": "Will Oldham - So far and here we are",
        "genre": "Country",
        "album" : "I made a place",
        "rating": []
    },
    {
        "src": "music/Will_Oldham-Stable_Will.mp3",
        "trackName": "Will Oldham - Stable will",
        "genre": "Country",
        "album" : "I made a place",
        "rating": []
    },
    {
        "src": "music/Will_Oldham-The_Risen_Lord.mp3",
        "trackName": "Will Oldham - The risen Lord",
        "genre": "Country",
        "album" : "I made a place",
        "rating": []
    },
    {
        "src": "music/Will_Oldham-The_Way.mp3",
        "trackName": "Will Oldham - The way",
        "genre": "Country",
        "album" : "I made a place",
        "rating": []
    },
    {
        "src": "music/Will_Oldham-Drinking_Woman.mp3",
        "trackName": "Will Oldham - Drinking Woman",
        "genre": "Country",
        "album" : "I made a place",
        "rating": []
    },
    
    {
        "src": "music/BTS-Go_go.mp3",
        "trackName": "BTS - Go go",
        "genre": "K-pop",
        "album" : "Love Yourself: Her",
        "rating": []
    },
    {
        "src": "music/BTS-2u_(cover).mp3",
        "trackName": "BTS - 2u cover",
        "genre": "K-pop",
        "album" : "Love Yourself: Her",
        "rating": []
    },
    {
        "src": "music/BTS-Blood_sweat_tears.mp3",
        "trackName": "BTS - Blood sweat&tears",
        "genre": "K-pop",
        "album" : "Blood Sweat & Tears",
        "rating": []
    },
    {
        "src": "music/BTS-Fire.mp3",
        "trackName": "BTS - Fire",
        "genre": "K-pop",
        "album" : "The Most Beautiful Moment in Life: Young Forever",
        "rating": []
    },
    {
        "src": "music/BTS-Save_me.mp3",
        "trackName": "BTS - Save me",
        "genre": "K-pop",
        "album" : "The Most Beautiful Moment in Life: Young Forever",
        "rating": []
    },
    {
        "src": "music/BTS-Boy_with_luv.mp3",
        "trackName": "BTS - Boy with luv",
        "genre": "K-pop",
        "album" : "Map of the Soul: Persona",
        "rating": []
    },
    {
        "src": "music/BTS-Best_of_me.mp3",
        "trackName": "BTS - Best of me",
        "genre": "K-pop",
        "album" : "Love Yourself: Her",
        "rating": []
    },
    {
        "src": "music/Jennie-Solo.mp3",
        "trackName": "Jennie - Solo",
        "genre": "K-pop",
        "album" : "Solo",
        "rating": []
    },
    {
        "src": "music/GOT7-You_calling_my_name.mp3",
        "trackName": "GOT7 - You calling my name",
        "genre": "K-pop",
        "album" : "Call my name",
        "rating": []
    },
    {
        "src": "music/Miles_Davis-Lonely_fire.mp3",
        "trackName": "Miles Davis - Lonely fire",
        "genre": "Jazz",
        "album" : "Big Fun",
        "rating": []
    },
    {
        "src": "music/Pleasurekraft-Coltrane.mp3",
        "trackName": "Pleasurekraft - Coltrane",
        "genre": "Jazz",
        "album" : "Coltrane / Sexus",
        "rating": []
    },
    {
        "src": "music/Norah_Jones-Say_goodbye.mp3",
        "trackName": "Norah Jones - Say goodbye",
        "genre": "Jazz",
        "album" : "Little Broken Hearts",
        "rating": []
    },
    {
        "src": "music/Norah_Jones-Sunrise.mp3",
        "trackName": "Norah Jones - Sunrise",
        "genre": "Jazz",
        "album" : "Feels like Home",
        "rating": []
    },
    {
        "src": "music/Sammy_Davis-There_will_never_be_another_you.mp3",
        "trackName": "Sammy Davis - There will never be another you",
        "genre": "Jazz",
        "album" : "There will never be another you",
        "rating": []
    },
    {
        "src": "music/Buddy_Guy-Night_flight.mp3",
        "trackName": "Frenk Sinatra - Strangers in the night",
        "genre": "Jazz",
        "album" : "Strangers in the Night",
        "rating": []
    },
    {
        "src": "music/Frank_Sinatra-Thats_life.mp3",
        "trackName": "Frenk Sinatra - Thats life",
        "genre": "Jazz",
        "album" : "That's Life",
        "rating": []
    },
    {
        "src": "music/Frank_Sinatra-I_love_you_baby.mp3",
        "trackName": "Frenk Sinatra - Love you baby",
        "genre": "Jazz",
        "album" : "That's Life",
        "rating": []
    },
    {
        "src": "music/Frenk_Sinatra-My_way.mp3",
        "trackName": "Frenk Sinatra - My way",
        "genre": "Jazz",
        "album" : "My way",
        "rating": []
    },
    {
        "src": "music/John_Coltrane-Equinox.mp3",
        "trackName": "John Coltrane - Equinox",
        "genre": "Jazz",
        "album" : "Equinox",
        "rating": []
    },
    {
        "src": "music/John_Coltrane-Naima.mp3",
        "trackName": "John Coltrane - Naima",
        "genre": "Jazz",
        "album" : "Naima",
        "rating": []
    },
    {
        "src": "music/Norah_Jones-Chasing_pirates.mp3",
        "trackName": "Norah Jones - Chasing pirates",
        "genre": "Jazz",
        "album" : "The Fall",
        "rating": []
    },
    {
        "src": "music/Miles_Davis-The_gaslight_anthem.mp3",
        "trackName": "Miles Davis - The gaslight anthem",
        "genre": "Jazz",
        "album" : "The gaslight anthem",
        "rating": []
    },
    {
        "src": "music/Louis_Armstrong-Mack_the_knife.mp3",
        "trackName": "Louis Armstrong - Mack the knife",
        "genre": "Jazz",
        "album" : "Mack the knife",
        "rating": []
    },
    {
        "src": "music/Louis_Armstrong_Frank_Sinatra-The_christmas_song.mp3",
        "trackName": "Louis Armstrong & Frank Sinatra - The christmas song",
        "genre": "Jazz",
        "album" : "It's Christmas Time",
        "rating": []
    },
    {
        "src": "music/Louis_Armstrong-What_a_wonderful_world.mp3",
        "trackName": "Louis Armstrong - What a wonderful world",
        "genre": "Jazz",
        "album" : "What a Wonderful World",
        "rating": []
    },
    {
        "src": "music/Kraftwerk-The_man_machine.mp3",
        "trackName": "Kraftwerk - The man machine",
        "genre": "Electro",
        "album" : "The Man-Machine",
        "rating": []
    },
    {
        "src": "music/Kraftwerk-Kraftwerk_popcorn.mp3",
        "trackName": "Kraftwerk - Kraftwerk popcorn",
        "genre": "Electro",
        "album" : "Music to Moog By",
        "rating": []
    },
    {
        "src": "music/Kraftwerk-Die_roboter.mp3",
        "trackName": "Kraftwerk - Die roboter",
        "genre": "Electro",
        "album" : "The robots",
        "rating": []
    },
    {
        "src": "music/Deadmouse-Moar_ghosts_n_stuff.mp3",
        "trackName": "Deadmouse - Moar ghosts on stuff",
        "genre": "Electro",
        "album" : "Ghosts 'n' Stuff",
        "rating": []
    },
    {
        "src": "music/Deadmouse-Not_exactly.mp3",
        "trackName": "Deadmouse - Not exactly",
        "genre": "Electro",
        "album" : "Not exactly",
        "rating": []
    },
    {
        "src": "music/Tiesto-Ritual.mp3",
        "trackName": "Tiesto - Ritual",
        "genre": "Electro",
        "album" : "Ritual",
        "rating": []
    },
    {
        "src": "music/Tiesto-Grapevine_carta_remix.mp3",
        "trackName": "Tiesto - Grapevine carta(remix)",
        "genre": "Electro",
        "album" : "Carta",
        "rating": []
    },
    {
        "src": "music/Scrillex-Monster.mp3",
        "trackName": "Scrillex - Monster",
        "genre": "Electro",
        "album" : "Scary Monsters and Nice Sprites",
        "rating": []
    },
    {
        "src": "music/Scrillex-Kill_everybody.mp3",
        "trackName": "Scrillex - Kill everbody",
        "genre": "Electro",
        "album" : "Scary Monsters and Nice Sprites",
        "rating": []
    },
    {
        "src": "music/Scrillex-First_of_the_year.mp3",
        "trackName": "Scrillex - First of the year",
        "genre": "Electro",
        "album" : "Scary Monsters and Nice Sprites",
        "rating": []
    },
    {
        "src": "music/Deadmouse-Deadmouse.mp3",
        "trackName": "Deadmouse - Deadmouse",
        "genre": "Electro",
        "album" : "Random Album Title",
        "rating": []
    },
    {
        "src": "music/Tiesto-God_is_a_dancer.mp3",
        "trackName": "Tiesto - God is a dancer",
        "genre": "Electro",
        "album" : "High Expectations",
        "rating": []
    },
    {
        "src": "music/Daft_Punk-One_more_time.mp3",
        "trackName": "Daft Punk - One more time",
        "genre": "Electro",
        "album" : "Alive 2007",
        "rating": []
    },
    {
        "src": "music/Daft_Punk-Get_lucky_original.mp3",
        "trackName": "Daft Punk - Get lucky original",
        "genre": "Electro",
        "album" : "Get Lucky",
        "rating": []
    },
    {
        "src": "music/Daft_Punk-Harder_better_faster_stronger.mp3",
        "trackName": "Daft Punk - Harder, better, faster, stronger",
        "genre": "Electro",
        "album" : "Discovery",
        "rating": []
    },
    {
        "src": "music/Muddy_Waters-She_moves_me.mp3",
        "trackName": "Muddy Waters - She moves me",
        "genre": "Blues",
        "album" : "Authorized Bootleg",
        "rating": []
    },
    {
        "src": "music/Muddy_Waters-Muddy_jumps_one.mp3",
        "trackName": "Muddy Waters - Muddy jumps one",
        "genre": "Blues",
        "album" : "Muddy Jumps One",
        "rating": []
    },
    {
        "src": "music/Muddy_Waters-They_call_me_muddy_waters.mp3",
        "trackName": "Muddy Waters - They call me Muddy Waters",
        "genre": "Blues",
        "album" : "They Call Me Muddy Waters",
        "rating": []
    },
    {
        "src": "music/Robert_Johnson-Sweet_home_chicago.mp3",
        "trackName": "Robert Johnson - Sweet home Chicago",
        "genre": "Blues",
        "album" : "Sweet home Chicago",
        "rating": []
    },
    {
        "src": "music/Robert_Johnson-I_believe_ill_dust_my_broom.mp3",
        "trackName": "Robert Johnson - I belive i'll dust my broom",
        "genre": "Blues",
        "album" : "King Of The Delta Blues Singers (Volume 2)",
        "rating": []
    },
    {
        "src": "music/Tom_Hooker-Talk_with_your_body.mp3",
        "trackName": "Tom Hooker - Talk with your body",
        "genre": "Blues",
        "album" : "Only One (LP)",
        "rating": []
    },
    {
        "src": "music/BuddyGuy-Nightflight.mp3",
        "trackName": "Buddy Guy - Night light",
        "genre": "Blues",
        "album" : "The real deal",
        "rating": []
    },
    {
        "src": "music/John_Lee_Hooker-Boom_boom.mp3",
        "trackName": "John Lee Hooker - Boom boom",
        "genre": "Blues",
        "album" : "Boom boom",
        "rating": []
    },
    {
        "src": "music/Buddy_Guy-Crazy_love.mp3",
        "trackName": "Buddy Guy - Crazy Love",
        "genre": "Blues",
        "album" : "I Left My Blues in San Francisco",
        "rating": []
    },
    {
        "src": "music/John_Lee_Hooker-The_healer.mp3",
        "trackName": "John Lee Hooker - The healer",
        "genre": "Blues",
        "album" : "The Healer",
        "rating": []
    },
    {
        "src": "music/Robert_Johnson-Cross_road_blues.mp3",
        "trackName": "Robert Johnson - Cross road blues",
        "genre": "Blues",
        "album" : "Cross Road Blues",
        "rating": []
    },
    {
        "src": "music/Albert_King-Born_under_a_bad_sign.mp3",
        "trackName": "Albert King - Born under a bad sign",
        "genre": "Blues",
        "album" : "Born Under a Bad Sign",
        "rating": []
    },
    {
        "src": "music/Albert_King-Call_it_stormy_mondayalbert_king.mp3",
        "trackName": "Albert King - Call it stormy mondayalbert king",
        "genre": "Blues",
        "album" : "Call It Stormy Monday",
        "rating": []
    },
    {
        "src": "music/Albert_King-For_the_love_of_a_woman.mp3",
        "trackName": "Albert King - For the love of a woman",
        "genre": "Blues",
        "album" : "Lovejoy",
        "rating": []
    },
    {
        "src": "music/Buddy_Guy-Let_me_love_you_baby.mp3",
        "trackName": "Buddy Guy - Let me love you baby",
        "genre": "Blues",
        "album" : "I Was Walking Through the Woods",
        "rating": []
    },
    {
        "src": "music/Josh_Wink-Dont_laugh.mp3",
        "trackName": "Josh Wink - Don't laugh",
        "genre": "Techno",
        "album" : "Don't Laugh (Manoo Remixes)",
        "rating": []
    },
    {
        "src": "music/Kink-Da_funk.mp3",
        "trackName": "Kink - Da funk",
        "genre": "Techno",
        "album" : "The funk",
        "rating": []
    },
    {
        "src": "music/Kink-Cloud_generator.mp3",
        "trackName": "Kink - Cloud generator",
        "genre": "Techno",
        "album" : "Cloud Generator EP",
        "rating": []
    },
    {
        "src": "music/Josh_Wink-Are_you_there.mp3",
        "trackName": "Josh Wink - Are you there",
        "genre": "Techno",
        "album" : "Are You There",
        "rating": []
    },
    {
        "src": "music/Josh_Wink-Wink.mp3",
        "trackName": "Josh Wink - Wink",
        "genre": "Techno",
        "album" : "When a banana was just a banana",
        "rating": []
    },
    {
        "src": "music/Christian_Hornbostel-Etat_desprit.mp3",
        "trackName": "Christian Hornbostel - Etat disprit",
        "genre": "Techno",
        "album" : "Happy Hour Chillhouse",
        "rating": []
    },
    {
        "src": "music/Adam_Beyer-Remainings111.mp3",
        "trackName": "Adam Beyer - Remainings 111",
        "genre": "Techno",
        "album" : "Remainings III",
        "rating": []
    },
    {
        "src": "music/Christian_Hornbostel-So_much_music(dub_mix).mp3",
        "trackName": "Christian Hornbostel - So much music(dub mix)",
        "genre": "Techno",
        "album" : "House mixtape",
        "rating": []
    },
    {
        "src": "music/Adam_Beyer-Ignition_key.mp3",
        "trackName": "Adam Beyer - Ignition Key",
        "genre": "Techno",
        "album" : "Ignition Key",
        "rating": []
    },
    {
        "src": "music/Tiger_Stripes-Spirited_away.mp3",
        "trackName": "Tiger Stripes - Spirited away",
        "genre": "Techno",
        "album" : "Spirited Away / Amphytrion",
        "rating": []
    },
    {
        "src": "music/Kink-e79.mp3",
        "trackName": "Tink - e79",
        "genre": "Techno",
        "album" : "Voicemails",
        "rating": []
    },
    {
        "src": "music/Hornbostel_Thammer-Shadowing_ultradub.mp3",
        "trackName": "Hornbostel Thammer - Shadowing(ultradub)",
        "genre": "Techno",
        "album" : "Shadowing",
        "rating": []
    },
    {
        "src": "music/Adam_Beyer-Sthlm.mp3",
        "trackName": "Adam Beyer - Sthlm",
        "genre": "Techno",
        "album" : "Nutcrusch",
        "rating": []
    },
    {
        "src": "music/Tiger_Stripes_feat_Hanna_Hais-Consecration.mp3",
        "trackName": "Tiger Stripes feat Hanna Hais - Consecration",
        "genre": "Techno",
        "album" : "Safari",
        "rating": []
    },
    {
        "src": "music/Tiger_Stripes-Runaways.mp3",
        "trackName": "Tiger Stripes - Runaways",
        "genre": "Techno",
        "album" : "After the Sun",
        "rating": []
    }
]